<window xmlns="http://jmix.io/schema/ui/window"
        caption="msg://application.caption">
    <layout>
        <cssLayout id="horizontalWrap"
                   stylename="jmix-drawer-layout">
            <drawer id="drawer"
                    expandOnHover="true">
                <cssLayout id="controlPanel"
                           stylename="control-panel"
                           width="100%">
                    <button id="resetBtn" caption="msg://resetBtn.caption" icon="ROTATE_LEFT"
                            width="100%"
                            stylename="secondary"/>
                    <button id="downloadBtn" caption="msg://downloadBtn.caption" icon="DOWNLOAD"
                            stylename="primary"
                            width="100%"/>
                    <button id="uploadBtn" caption="msg://uploadBtn.caption" icon="UPLOAD"
                            width="100%"/>
                </cssLayout>
                <scrollBox id="settingsPanel"
                           margin="true"
                           stylename="settings-panel"
                           spacing="true">
                    <vbox margin="true" width="100%" stylename="card">
                        <vbox>
                            <radioButtonGroup id="baseThemeModeField"
                                              orientation="horizontal"
                                              captionProperty="name"
                                              align="MIDDLE_CENTER"/>
                        </vbox>
                        <vbox>
                            <label id="templateLabel"
                                   align="MIDDLE_LEFT"
                                   stylename="bold"
                                   value="msg://templateLabel.value" width="100%"/>
                            <comboBox id="templateField"
                                      width="100%"
                                      nullOptionVisible="false"/>
                        </vbox>
                    </vbox>
                    <hbox spacing="true" width="100%">
                        <checkBox id="advancedModeValue"
                                  align="MIDDLE_LEFT"
                                  captionAsHtml="true"
                                  caption="msg://advancedModeLabel.value"/>
                    </hbox>
                </scrollBox>
                <cssLayout id="controlBox"
                           stylename="jmix-drawer-footer"
                           width="100%">
                    <button id="collapseDrawerButton"
                            icon="CHEVRON_LEFT"
                            stylename="jmix-drawer-collapse-button"
                            description="msg://sideMenuCollapse"/>
                </cssLayout>
            </drawer>
            <workArea id="workArea"
                      stylename="jmix-workarea"
                      height="100%"
                      width="100%">
                <initialLayout margin="true"
                               spacing="true"
                               expand="componentSamples">
                    <fragment id="componentSamples" screen="helium_ComponentSamplesFragment"/>
                </initialLayout>
            </workArea>
        </cssLayout>
    </layout>
</window>